{
  "sec-comments": {
    "title": "SEC Comment Letters \u2014 The Full Breakdown",
    "subtitle": "Why the government's letters to companies are basically cheat codes",
    "sections": [
      {
        "heading": "What Even IS EDGAR?",
        "body": "EDGAR stands for **Electronic Data Gathering, Analysis, and Retrieval**. It's the SEC's free public database \u2014 basically a massive digital filing cabinet where every public company (Apple, Tesla, GameStop, all of them) is legally required to dump their financial reports.\n\nThe SEC is the **Securities and Exchange Commission** \u2014 the federal agency that watches over Wall Street like a hall monitor. They were created after the 1929 stock market crash to make sure companies can't scam investors.\n\nEDGAR has existed since 1996. Before that, you had to physically go to a SEC office in Washington DC and photocopy documents. Nightmare.\n\n**Fun fact:** The name \"EDGAR\" was originally just a project acronym, but it stuck. There's no actual person named Edgar. Sorry."
      },
      {
        "heading": "So What Are Comment Letters?",
        "body": "Here's the flow:\n\n1. A company files their quarterly or annual report on EDGAR\n2. SEC staff (called \"reviewers\") read through it\n3. If something looks sketchy, confusing, or incomplete, they send a **comment letter** \u2014 basically a formal \"hey, explain yourself\" letter\n4. The company has to respond with clarification\n5. Back-and-forth continues until the SEC is satisfied\n6. **ALL of this is public record on EDGAR**\n\nThink of it like this: You submit your homework. Your teacher writes \"explain question 3\" in red pen. You have to write a response. Except this is a billion-dollar company and the teacher is a federal regulator, and the homework is whether they're cooking their books."
      },
      {
        "heading": "Why Should I Care?",
        "body": "Because comment letters are **early warning signals**.\n\nAcademic studies have shown that companies receiving certain types of SEC comments are significantly more likely to:\n- Restate their earnings later (admitting their numbers were wrong)\n- Get sued by investors\n- See their stock price drop\n- Go bankrupt (in extreme cases, like going-concern comments)\n\n**Exhibit A: The Going Concern Bomb**\n\nIf the SEC asks \"does this company have enough cash to survive the next 12 months?\" \u2014 that's a GOING CONCERN warning. It's the nuclear option. The SEC is basically saying \"we're not sure this company is going to make it.\"\n\nCompanies that receive going concern warnings have an **80% chance of bankruptcy within 2 years**. That's not a typo. Eighty percent.\n\n**Exhibit B: Revenue Recognition**\n\nIf the SEC questions HOW a company counts its revenue, pay attention. This is how Enron fooled everyone for years \u2014 they were counting revenue before they actually earned it. Like marking your test as \"A+\" before taking it.\n\n**Exhibit C: Material Weakness**\n\nWhen the SEC says a company has \"material weakness in internal controls,\" it means their financial reporting systems are broken. You literally can't trust the numbers they're showing you."
      },
      {
        "heading": "The System (Visualized)",
        "body": "```\n\u250c\u2500\u2500\u2500\u2500\u2500\u2500\u2500\u2500\u2500\u2500\u2500\u2500\u2500\u2500\u2500\u2500\u2500\u2500\u2500\u2500\u2500\u2500\u2500\u2500\u2500\u2500\u2500\u2500\u2500\u2500\u2500\u2500\u2500\u2500\u2500\u2500\u2500\u2500\u2500\u2500\u2500\u2500\u2500\u2500\u2500\u2500\u2500\u2500\u2500\u2500\u2500\u2500\u2500\u2500\u2500\u2500\u2500\u2510\n\u2502                    THE EDGAR PIPELINE                    \u2502\n\u251c\u2500\u2500\u2500\u2500\u2500\u2500\u2500\u2500\u2500\u2500\u2500\u2500\u2500\u2500\u2500\u2500\u2500\u2500\u2500\u2500\u2500\u2500\u2500\u2500\u2500\u2500\u2500\u2500\u2500\u2500\u2500\u2500\u2500\u2500\u2500\u2500\u2500\u2500\u2500\u2500\u2500\u2500\u2500\u2500\u2500\u2500\u2500\u2500\u2500\u2500\u2500\u2500\u2500\u2500\u2500\u2500\u2500\u2524\n\u2502                                                          \u2502\n\u2502  Company Files 10-K/10-Q \u2500\u2500\u2500\u2500\u2500\u2500\u25ba EDGAR Database         \u2502\n\u2502         \u2502                              \u2502                 \u2502\n\u2502         \u2502 (every 10 min)               \u2502                 \u2502\n\u2502         \u25bc                              \u25bc                 \u2502\n\u2502  SEC Reviewers Read \u2500\u2500\u2500\u2500\u2500\u2500\u25ba Questions?                   \u2502\n\u2502         \u2502                        \u2502                       \u2502\n\u2502         \u2502                        \u25bc                       \u2502\n\u2502         \u2502              Comment Letter Sent               \u2502\n\u2502         \u2502              (PUBLIC on EDGAR)                 \u2502\n\u2502         \u2502                        \u2502                       \u2502\n\u2502         \u2502                        \u25bc                       \u2502\n\u2502         \u2502              Company Responds                  \u2502\n\u2502         \u2502              (PUBLIC on EDGAR)                 \u2502\n\u2502         \u2502                        \u2502                       \u2502\n\u2502         \u25bc                        \u25bc                       \u2502\n\u2502  \u250c\u2500\u2500\u2500\u2500\u2500\u2500\u2500\u2500\u2500\u2500\u2500\u2500\u2500\u2500\u2500\u2500\u2500\u2500\u2500\u2500\u2500\u2500\u2500\u2500\u2500\u2500\u2500\u2500\u2500\u2500\u2500\u2500\u2500\u2500\u2500\u2500\u2500\u2500\u2510               \u2502\n\u2502  \u2502  OUR BOTS: Parse \u2192 Score \u2192 Alert     \u2502               \u2502\n\u2502  \u2502  Materiality Score: 1-10             \u2502               \u2502\n\u2502  \u2502  Keywords detected: going concern,   \u2502               \u2502\n\u2502  \u2502  revenue recognition, fraud, etc.    \u2502               \u2502\n\u2502  \u2514\u2500\u2500\u2500\u2500\u2500\u2500\u2500\u2500\u2500\u2500\u2500\u2500\u2500\u2500\u2500\u2500\u2500\u2500\u2500\u2500\u2500\u2500\u2500\u2500\u2500\u2500\u2500\u2500\u2500\u2500\u2500\u2500\u2500\u2500\u2500\u2500\u2500\u2500\u2518               \u2502\n\u2502                    \u2502                                     \u2502\n\u2502                    \u25bc                                     \u2502\n\u2502  \u250c\u2500\u2500\u2500\u2500\u2500\u2500\u2500\u2500\u2500\u2500\u2500\u2500\u2500\u2500\u2500\u2500\u2500\u2500\u2500\u2500\u2500\u2500\u2500\u2500\u2500\u2500\u2500\u2500\u2500\u2500\u2500\u2500\u2500\u2500\u2500\u2500\u2500\u2500\u2510               \u2502\n\u2502  \u2502  YOUR DASHBOARD: Ranked by severity  \u2502               \u2502\n\u2502  \u2502  Click card \u2192 see full breakdown     \u2502               \u2502\n\u2502  \u2502  Difficulty + Capital needed shown   \u2502               \u2502\n\u2502  \u2514\u2500\u2500\u2500\u2500\u2500\u2500\u2500\u2500\u2500\u2500\u2500\u2500\u2500\u2500\u2500\u2500\u2500\u2500\u2500\u2500\u2500\u2500\u2500\u2500\u2500\u2500\u2500\u2500\u2500\u2500\u2500\u2500\u2500\u2500\u2500\u2500\u2500\u2500\u2518               \u2502\n\u2502                                                          \u2502\n\u2514\u2500\u2500\u2500\u2500\u2500\u2500\u2500\u2500\u2500\u2500\u2500\u2500\u2500\u2500\u2500\u2500\u2500\u2500\u2500\u2500\u2500\u2500\u2500\u2500\u2500\u2500\u2500\u2500\u2500\u2500\u2500\u2500\u2500\u2500\u2500\u2500\u2500\u2500\u2500\u2500\u2500\u2500\u2500\u2500\u2500\u2500\u2500\u2500\u2500\u2500\u2500\u2500\u2500\u2500\u2500\u2500\u2500\u2518\n```"
      },
      {
        "heading": "How Hedge Funds Use This",
        "body": "Big hedge funds pay **$100K-$500K/year** for premium tools that basically just read EDGAR faster and add analytics. Services like RavenPack, Sentieo, and others charge insane premiums for what amounts to \"we read the SEC comments before you do.\"\n\nOur system does the same thing for free. The data is public. The SEC publishes it for free. We just automated the boring reading part.\n\n**The edge isn't the data \u2014 it's the speed of reading it.** If you see a comment letter before the market fully digests it, you have a window where the stock hasn't moved yet. That's the opportunity."
      },
      {
        "heading": "How to Trade These Signals",
        "body": "**Difficulty: Easy to Medium**\n**Capital needed: $100-$10K**\n**Timeframe: 2-8 weeks (high severity) or 1-3 months (medium)**\n\nStep-by-step:\n1. Check the signal card for materiality score (7+ = serious)\n2. Read the specific questions the SEC asked\n3. Look at the company's response (if available)\n4. Decide: Is this a real problem or just routine SEC review?\n5. If real problem \u2192 consider shorting or staying away\n6. If routine \u2192 the stock might actually be a buy (overreaction)\n\n**Golden rule:** Not every comment letter means doom. The SEC sends hundreds per year. Most are routine. The art is knowing which ones matter. That's what our scoring system does for you."
      }
    ]
  },
  "patent-cliffs": {
    "title": "Patent Cliffs \u2014 When Drug Monopolies Die",
    "subtitle": "Why knowing expiration dates can make you a fortune",
    "sections": [
      {
        "heading": "The Basic Concept",
        "body": "When a pharma company invents a new drug, they get a **20-year patent**. That means NOBODY else can make that drug for 20 years. Total monopoly. They can charge whatever they want.\n\nWhen the patent expires? **Game over for the brand name.** Any company can now make a \"generic\" version \u2014 same drug, same formula, but costs 80-90% less.\n\nThis is called a **patent cliff** because brand-name sales FALL OFF A CLIFF when generics enter.\n\n**Exhibit A: Lipitor (Pfizer)**\n- Peak sales: **$12.4 BILLION per year** (2006)\n- Patent expired: November 2011\n- Sales within 1 year: **$2.3 billion**\n- That's an **82% drop** in revenue from one drug\n\n**Exhibit B: Humira (AbbVie)**\n- Peak sales: **$21 billion per year**\n- Patent cliffs started: 2023\n- Multiple biosimilar competitors entered\n- Revenue expected to drop 30-40% by 2025\n\n**Exhibit C: Keytruda (Merck)**\n- World's best-selling drug: **$25 billion/year**\n- Patent expires: 2028\n- Merck is desperately trying to extend or find replacements"
      },
      {
        "heading": "Why Does This Matter to You?",
        "body": "Because the market doesn't always price in patent cliffs immediately. Sometimes there's a 6-18 month window where:\n- The cliff is approaching (publicly known)\n- Wall Street analysts are still modeling peak sales\n- The stock hasn't dropped yet\n\n**If you know a patent cliff is coming, and the market hasn't priced it in, you can short the stock and profit from the crash.**\n\nBut it's not that simple:\n- Companies try to extend patents (evergreening)\n- New indications can extend revenue\n- Buyouts and acquisitions can change the math\n- Sometimes the cliff is already priced in\n\n**That's why we track this.** We show you what's coming, when, and how severe."
      },
      {
        "heading": "The Patent Cliff Timeline",
        "body": "```\n\u250c\u2500\u2500\u2500\u2500\u2500\u2500\u2500\u2500\u2500\u2500\u2500\u2500\u2500\u2500\u2500\u2500\u2500\u2500\u2500\u2500\u2500\u2500\u2500\u2500\u2500\u2500\u2500\u2500\u2500\u2500\u2500\u2500\u2500\u2500\u2500\u2500\u2500\u2500\u2500\u2500\u2500\u2500\u2500\u2500\u2500\u2500\u2500\u2500\u2500\u2500\u2500\u2500\u2500\u2500\u2500\u2500\u2500\u2500\u2500\u2500\u2510\n\u2502              THE PATENT CLIFF LIFECYCLE                     \u2502\n\u251c\u2500\u2500\u2500\u2500\u2500\u2500\u2500\u2500\u2500\u2500\u2500\u2500\u2500\u2500\u2500\u2500\u2500\u2500\u2500\u2500\u2500\u2500\u2500\u2500\u2500\u2500\u2500\u2500\u2500\u2500\u2500\u2500\u2500\u2500\u2500\u2500\u2500\u2500\u2500\u2500\u2500\u2500\u2500\u2500\u2500\u2500\u2500\u2500\u2500\u2500\u2500\u2500\u2500\u2500\u2500\u2500\u2500\u2500\u2500\u2500\u2524\n\u2502                                                             \u2502\n\u2502  YEAR 0: Drug Approved                                      \u2502\n\u2502  \u251c\u2500\u2500 Patent protection begins                               \u2502\n\u2502  \u251c\u2500\u2500 Monopoly pricing: $10,000/month treatment              \u2502\n\u2502  \u2514\u2500\u2500 Stock rises on blockbuster potential                   \u2502\n\u2502                                                             \u2502\n\u2502  YEAR 10: Mid-life                                          \u2502\n\u2502  \u251c\u2500\u2500 Sales peak: $10-20 billion/year                        \u2502\n\u2502  \u251c\u2500\u2500 Analysts love it                                       \u2502\n\u2502  \u2514\u2500\u2500 Patent cliff is \"on the radar\" but distant             \u2502\n\u2502                                                             \u2502\n\u2502  YEAR 15-18: Cliff Approaching                              \u2502\n\u2502  \u251c\u2500\u2500 Generics manufacturers file for approval               \u2502\n\u2502  \u251c\u2500\u2500 Lawsuits begin (patent challenges)                     \u2502\n\u2502  \u251c\u2500\u2500 Smart money starts shorting                            \u2502\n\u2502  \u2514\u2500\u2500 Stock starts declining                                 \u2502\n\u2502                                                             \u2502\n\u2502  YEAR 20: PATENT EXPLODES                                   \u2502\n\u2502  \u251c\u2500\u2500 Generics flood the market                              \u2502\n\u2502  \u251c\u2500\u2500 Brand price drops 50-90%                               \u2502\n\u2502  \u251c\u2500\u2500 Sales crash 80%                                        \u2502\n\u2502  \u2514\u2500\u2500 Stock drops 20-80%                                     \u2502\n\u2502                                                             \u2502\n\u2502  YEAR 20+: New Normal                                       \u2502\n\u2502  \u251c\u2500\u2500 Brand survives on loyalty + new formulations           \u2502\n\u2502  \u251c\u2500\u2500 Revenue stabilizes at 20% of peak                      \u2502\n\u2502  \u2514\u2500\u2500 Company must find new drugs or die                     \u2502\n\u2502                                                             \u2502\n\u2514\u2500\u2500\u2500\u2500\u2500\u2500\u2500\u2500\u2500\u2500\u2500\u2500\u2500\u2500\u2500\u2500\u2500\u2500\u2500\u2500\u2500\u2500\u2500\u2500\u2500\u2500\u2500\u2500\u2500\u2500\u2500\u2500\u2500\u2500\u2500\u2500\u2500\u2500\u2500\u2500\u2500\u2500\u2500\u2500\u2500\u2500\u2500\u2500\u2500\u2500\u2500\u2500\u2500\u2500\u2500\u2500\u2500\u2500\u2500\u2500\u2518\n```"
      },
      {
        "heading": "How to Trade Patent Cliffs",
        "body": "**Difficulty: Medium to Hard**\n**Capital needed: $1K-$10K+**\n**Timeframe: 6-18 months**\n\nThe playbook:\n1. Identify drugs expiring in the next 1-3 years\n2. Check the brand-name company's revenue dependence on that drug\n3. Look for \"cliff hedging\" \u2014 are they already diversifying?\n4. If over-dependent and cliff is close \u2192 short opportunity\n5. If already priced in \u2192 look for generic companies to go LONG\n\n**Generic companies WIN from patent cliffs.** Companies like Teva, Sandoz, and Mylan make their living off these expirations. When a major cliff approaches, generics stock up.\n\n**Pro tip:** The FDA maintains a \"Orange Book\" \u2014 the official list of drug patents and exclusivity. It's public. We cross-reference it with our data."
      }
    ]
  },
  "insider-trading": {
    "title": "Insider Trading \u2014 When the Boss Bets on Himself",
    "subtitle": "Why CEO stock purchases are the most underrated signal in investing",
    "sections": [
      {
        "heading": "What Is Insider Trading (The Legal Kind)?",
        "body": "\"Insider trading\" sounds illegal, but the legal version is totally normal and actually one of the best signals in investing.\n\n**Legal insider trading:** When a CEO, director, or officer of a company buys or sells their OWN company's stock. They're required by law to report it within 2 business days on a form called **Form 4**. It's public record on EDGAR.\n\n**Illegal insider trading:** When someone trades based on material non-public information (like knowing a merger is happening before it's announced). That's the kind that sends people to prison.\n\nWe only track the legal kind. The form 4 filings. The ones where the boss is putting their own money on the line."
      },
      {
        "heading": "Why Do Insiders Trade?",
        "body": "There are two types of insider activity:\n\n**Buying (BULLISH signal):**\nWhen a CEO buys their own stock, they're saying \"I think this company is going up.\" They know the business better than any Wall Street analyst. They see the quarterly numbers before they're public. They know about new products, cost savings, upcoming deals.\n\nAcademic research shows insider buying beats the market by **6-8% per year** on average.\n\n**Selling (less informative):**\nInsiders sell for all kinds of reasons \u2014 diversification, college tuition, buying a house, pre-planned sales (10b5-1 forms). Selling doesn't necessarily mean bad news.\n\n**Cluster buying (STRONGEST signal):**\nWhen 3+ insiders buy at the same time? That's a cluster buy. It's one of the strongest signals in finance. Multiple insiders all voting with their wallets simultaneously = they all know something good is coming."
      },
      {
        "heading": "The Research",
        "body": "Studies going back decades show:\n\n- **Seyhun (1986):** Insiders earn ~5% abnormal returns on their purchases\n- **Jeng et al. (2003):** Insider purchases outperform by 6.2% annually\n- **Cohen et al. (2012):** \"Informative\" buys (not routine) show even stronger returns\n\nThe pattern: Insiders who buy aggressively (large amounts relative to their holdings) show the strongest future stock performance.\n\n**Why doesn't everyone just copy insiders?**\n1. Most people don't know how to read Form 4 filings\n2. The data is buried in EDGAR's messy index files\n3. There's a lot of noise (routine sales, tax-related selling)\n4. The edge is small \u2014 6-8% annually \u2014 so it's not a get-rich-quick scheme\n\nThat's exactly why we filter and score it for you."
      },
      {
        "heading": "The System",
        "body": "```\n\u250c\u2500\u2500\u2500\u2500\u2500\u2500\u2500\u2500\u2500\u2500\u2500\u2500\u2500\u2500\u2500\u2500\u2500\u2500\u2500\u2500\u2500\u2500\u2500\u2500\u2500\u2500\u2500\u2500\u2500\u2500\u2500\u2500\u2500\u2500\u2500\u2500\u2500\u2500\u2500\u2500\u2500\u2500\u2500\u2500\u2500\u2500\u2500\u2500\u2500\u2500\u2500\u2500\u2500\u2500\u2500\u2500\u2500\u2510\n\u2502              INSIDER TRADING DETECTION                   \u2502\n\u251c\u2500\u2500\u2500\u2500\u2500\u2500\u2500\u2500\u2500\u2500\u2500\u2500\u2500\u2500\u2500\u2500\u2500\u2500\u2500\u2500\u2500\u2500\u2500\u2500\u2500\u2500\u2500\u2500\u2500\u2500\u2500\u2500\u2500\u2500\u2500\u2500\u2500\u2500\u2500\u2500\u2500\u2500\u2500\u2500\u2500\u2500\u2500\u2500\u2500\u2500\u2500\u2500\u2500\u2500\u2500\u2500\u2500\u2524\n\u2502                                                          \u2502\n\u2502  CEO/Director buys $500K of company stock                \u2502\n\u2502         \u2502                                                \u2502\n\u2502         \u25bc                                                \u2502\n\u2502  Form 4 filed within 48 hours (PUBLIC on EDGAR)          \u2502\n\u2502         \u2502                                                \u2502\n\u2502         \u25bc                                                \u2502\n\u2502  Our bot scans EDGAR index every 3 hours                 \u2502\n\u2502         \u2502                                                \u2502\n\u2502         \u25bc                                                \u2502\n\u2502  Is this a CLUSTER? (3+ insiders same period)            \u2502\n\u2502         \u2502                                                \u2502\n\u2502    \u250c\u2500\u2500\u2500\u2500\u2534\u2500\u2500\u2500\u2500\u2510                                           \u2502\n\u2502    \u2502 YES     \u2502 NO                                        \u2502\n\u2502    \u25bc         \u25bc                                           \u2502\n\u2502  STRONG    NORMAL                                        \u2502\n\u2502  SIGNAL    SIGNAL                                        \u2502\n\u2502  (Score 8+) (Score 4-7)                                  \u2502\n\u2502    \u2502         \u2502                                           \u2502\n\u2502    \u25bc         \u25bc                                           \u2502\n\u2502  \u250c\u2500\u2500\u2500\u2500\u2500\u2500\u2500\u2500\u2500\u2500\u2500\u2500\u2500\u2500\u2500\u2500\u2500\u2500\u2500\u2500\u2500\u2500\u2500\u2500\u2500\u2500\u2500\u2500\u2500\u2500\u2500\u2500\u2500\u2500\u2500\u2500\u2500\u2500\u2510               \u2502\n\u2502  \u2502  YOUR DASHBOARD:                     \u2502               \u2502\n\u2502  \u2502  \u2022 Company name + ticker             \u2502               \u2502\n\u2502  \u2502  \u2022 Who bought + their title          \u2502               \u2502\n\u2502  \u2502  \u2022 How much they spent               \u2502               \u2502\n\u2502  \u2502  \u2022 Price per share                   \u2502               \u2502\n\u2502  \u2502  \u2022 Cluster? (yes/no)                 \u2502               \u2502\n\u2502  \u2502  \u2022 Difficulty + Capital needed       \u2502               \u2502\n\u2502  \u2514\u2500\u2500\u2500\u2500\u2500\u2500\u2500\u2500\u2500\u2500\u2500\u2500\u2500\u2500\u2500\u2500\u2500\u2500\u2500\u2500\u2500\u2500\u2500\u2500\u2500\u2500\u2500\u2500\u2500\u2500\u2500\u2500\u2500\u2500\u2500\u2500\u2500\u2500\u2518               \u2502\n\u2502                                                          \u2502\n\u2514\u2500\u2500\u2500\u2500\u2500\u2500\u2500\u2500\u2500\u2500\u2500\u2500\u2500\u2500\u2500\u2500\u2500\u2500\u2500\u2500\u2500\u2500\u2500\u2500\u2500\u2500\u2500\u2500\u2500\u2500\u2500\u2500\u2500\u2500\u2500\u2500\u2500\u2500\u2500\u2500\u2500\u2500\u2500\u2500\u2500\u2500\u2500\u2500\u2500\u2500\u2500\u2500\u2500\u2500\u2500\u2500\u2500\u2518\n```"
      },
      {
        "heading": "How to Trade Insider Signals",
        "body": "**Difficulty: Easy**\n**Capital needed: $100-$1K**\n**Timeframe: 1-6 months**\n\nThe playbook:\n1. Look for cluster buys (3+ insiders) \u2014 strongest signal\n2. Check the size of the purchase relative to their holdings\n3. CEO purchases > Director purchases (CEOs know more)\n4. Buy when insiders buy, hold for 3-6 months\n5. Set stop losses \u2014 insiders can be wrong too\n\n**Red flags to watch for:**\n- Insider buying but company is simultaneously issuing bad news (could be a distraction)\n- Very small purchases (token amounts just for optics)\n- Selling right after buying (look at the full picture)\n\n**The insider trading edge isn't about one trade. It's about a strategy of consistently following smart money over time.**"
      }
    ]
  },
  "going-concern": {
    "title": "Going Concern Warnings \u2014 The Nuclear Red Flag",
    "subtitle": "When the SEC says a company might not survive, pay attention",
    "sections": [
      {
        "heading": "What Is a Going Concern Warning?",
        "body": "A going concern warning is the most serious thing the SEC can say about a company.\n\nIn accounting, \"going concern\" means a company is assumed to be able to keep operating for the foreseeable future. It's a basic assumption behind all financial statements.\n\nWhen the SEC reviews a company and thinks \"this company might not survive the next 12 months,\" they require the company to disclose this in their filing. It's literally the SEC saying: **\"We're not sure this business is going to exist a year from now.\"**\n\nThis is not a prediction. It's a regulatory determination based on the company's financial position \u2014 cash flow, debt levels, ability to fund operations."
      },
      {
        "heading": "Why Is This So Serious?",
        "body": "The numbers don't lie:\n\n- **80% of companies that receive going concern warnings file for bankruptcy within 2 years**\n- Stock prices typically drop **30-60%** within 30 days of disclosure\n- Creditors may call in loans\n- Customers and suppliers may flee\n- Key employees often start leaving\n- The company's ability to raise new capital dries up\n\n**It's a death spiral.** And the SEC is basically putting up a giant neon sign that says \"this company might be dying.\"\n\n**Famous examples:**\n- **Enron (2001):** Going concern warnings appeared months before the full fraud was exposed. Stock went from $90 to $0.61\n- **Lehman Brothers (2008):** Substitute \"going concern\" with \"liquidity crisis\" \u2014 same result\n- **Wirecard (2020):** Going concern issues emerged before the \u20ac1.9 billion hole was discovered. Stock dropped 99% in 3 days"
      },
      {
        "heading": "How to Spot Them",
        "body": "Going concern warnings appear in:\n- 10-K annual reports (Item 7 \u2014 Management's Discussion)\n- 10-Q quarterly reports\n- Sometimes in 8-K material event filings\n\nLook for phrases like:\n- \"Substantial doubt about the entity's ability to continue as a going concern\"\n- \"Going concern uncertainty\"\n- \"May not have sufficient liquidity to fund operations\"\n- \"Recurring operating losses and negative cash flows\"\n\nOur system flags these automatically and scores them HIGH materiality (8-10)."
      },
      {
        "heading": "What to Do When You See One",
        "body": "**Difficulty: Easy (for selling) / Hard (for shorting)**\n**Capital needed: $0 if you already hold the stock**\n**Timeframe: Days to weeks**\n\nIf you own the stock:\n1. Read the filing \u2014 understand WHY they're warning\n2. Is it temporary (one-time charge) or structural (burning cash)?\n3. If structural \u2192 SELL. Don't wait. Don't hope. Sell.\n4. If temporary \u2014 monitor closely, set tight stop losses\n\nIf you don't own it:\n- Consider shorting (but be careful \u2014 short squeezes happen)\n- Or just avoid it entirely\n\n**The golden rule of going concerns: The 80% bankruptcy rate is not a suggestion. It's a warning. Respect it.**"
      }
    ]
  },
  "potential-earnings": {
    "title": "Potential Earnings \u2014 What Can You Actually Make?",
    "subtitle": "Realistic math on signal-based trading profits",
    "sections": [
      {
        "heading": "The Honest Truth",
        "body": "Let's be real: \"potential earnings\" on our signal cards are **optimistic scenarios**. They're what could happen IF everything plays out perfectly. In reality, you'll rarely capture the full upside.\n\nA good rule: **take profits at 50% of the indicated potential.** Greed is how beginners lose money.\n\nHere's the realistic breakdown by signal type:"
      },
      {
        "heading": "SEC Comment Signals",
        "body": "**Potential: 5-40% upside**\n**Timeframe: 2-8 weeks**\n**Difficulty: Easy to Medium**\n**Capital: $100-$10K**\n\nRealistic scenario:\n- High materiality comment (score 8+): Stock drops 10-30% over 2-4 weeks\n- If you short: capture 10-20% profit (not the full drop \u2014 you won't get perfect timing)\n- If you stay away: you avoid the drop, which is itself a win\n\n**Win rate:** About 55-60% of high-materiality comments lead to meaningful stock declines within 8 weeks\n\n**Key insight:** You don't need to predict every outcome. You need an edge that compounds over many trades."
      },
      {
        "heading": "Patent Cliff Signals",
        "body": "**Potential: 20-80% (short the brand name)**\n**Timeframe: 6-18 months**\n**Difficulty: Medium to Hard**\n**Capital: $1K-$10K+**\n\nRealistic scenario:\n- Brand-name stock drops 20-40% as cliff approaches\n- Generic company stock rises 10-30% as it prepares to launch\n- The biggest moves happen 6-12 months BEFORE the actual cliff\n\n**Win rate:** About 65-70% of major patent cliffs result in significant brand-name revenue declines\n\n**Key insight:** This is a longer-term play. Patience is required. The market is often slow to price in known cliffs."
      },
      {
        "heading": "Insider Trading Signals",
        "body": "**Potential: 5-30% over 6 months**\n**Timeframe: 1-6 months**\n**Difficulty: Easy**\n**Capital: $100-$1K**\n\nRealistic scenario:\n- Cluster buys (3+ insiders): Stock rises 5-15% over 3-6 months\n- Single large insider buy: Stock rises 3-8% over 3-6 months\n- The edge is small but consistent\n\n**Win rate:** About 55-60% for cluster buys, 52-55% for individual buys\n\n**Key insight:** Insider trading signals work best as part of a diversified strategy, not as a standalone strategy."
      },
      {
        "heading": "The Math of Compounding",
        "body": "Here's how the math works:\n\nIf you have a 55% win rate and you make 10% on winners, lose 5% on losers:\n- 100 trades: 55 wins \u00d7 10% = +550%\n- 100 trades: 45 losses \u00d7 5% = -225%\n- Net: +325% over 100 trades\n- Per trade average: +3.25%\n\nThat's a **massive** edge. Most professional fund managers would kill for +3% per trade.\n\n**The secret isn't picking winners. It's managing risk so your winners outpace your losers.**\n\nThis is why we show you:\n- Difficulty level (so you know what you're getting into)\n- Minimum capital (so you don't overextend)\n- Chance of fail (so you size your positions correctly)"
      }
    ]
  },
  "trading-guide": {
    "title": "How to Actually Trade These Signals",
    "subtitle": "A step-by-step playbook for turning intelligence into profit",
    "sections": [
      {
        "heading": "Step 1: Understand What You're Trading",
        "body": "You're not trading \"tips.\" You're trading **information asymmetry**.\n\nThe information is public. But most people don't read it. That's your edge.\n\nWhen you see a signal on our dashboard, you're seeing something that:\n- Is legally public (on EDGAR)\n- Required significant effort to produce (the SEC reviewed the filing)\n- Is scored for materiality (our system filtered out the noise)\n- Is actionable (you can actually do something with it)\n\nThis is not insider information. This is **superior processing of public information**."
      },
      {
        "heading": "Step 2: Assess the Signal",
        "body": "For each signal, check:\n\n**Materiality Score (1-10):**\n- 8-10: Serious SEC concern. High probability of market impact.\n- 5-7: Moderate concern. May or may not move the stock.\n- 1-4: Routine SEC review. Probably nothing.\n\n**Difficulty Level:**\n- Easy: Buy/sell stock on Robinhood. Anyone can do this.\n- Medium: Options trading. Requires approval + knowledge.\n- Hard: Shorting. Requires margin account + understanding of borrow costs.\n\n**Capital Needed:**\n- Don't overextend. A good rule: never risk more than 5% of your total portfolio on one signal.\n\n**Timeframe:**\n- Don't expect overnight moves. Give signals time to play out.\n- Set a reminder to check back in the indicated timeframe."
      },
      {
        "heading": "Step 3: The Trade",
        "body": "**For SEC Comment Signals (Bearish):**\n1. Read the comment letter (linked on the card)\n2. Assess: Is this serious or routine?\n3. If serious \u2192 Consider shorting or buying puts\n4. If routine \u2192 The stock might actually be a buy (overreaction)\n5. Set a stop loss at 5-10% above entry\n6. Take profits at 50% of indicated potential\n\n**For Patent Cliff Signals (Bearish on brand, bullish on generics):**\n1. Identify the cliff date\n2. Check if it's already priced in (has the stock already dropped?)\n3. If not priced in \u2192 Short the brand name or buy puts\n4. Alternatively \u2192 Long the generic company expected to launch\n5. Hold for 6-18 months\n\n**For Insider Trading Signals (Bullish):**\n1. Verify it's a cluster buy (3+ insiders)\n2. Check the purchase size (larger = stronger signal)\n3. Buy the stock\n4. Hold for 3-6 months\n5. Set a stop loss at 5-10% below entry"
      },
      {
        "heading": "Step 4: Risk Management",
        "body": "This is the most important step. Seriously.\n\n**The Golden Rules:**\n1. **Never invest more than you can afford to lose**\n2. **Always use stop losses** \u2014 5-10% on longs, 5-10% on shorts\n3. **Diversify** \u2014 Don't bet everything on one signal\n4. **Take profits early** \u2014 50% of potential is the target\n5. **Don't fall in love with positions** \u2014 If the thesis changes, exit\n\n**Position Sizing:**\n- High materiality (8-10): Max 10% of portfolio\n- Medium materiality (5-7): Max 5% of portfolio\n- Low materiality (1-4): Max 2% of portfolio\n\n**The Math:**\nIf you risk 5% per trade and have a 55% win rate:\n- 10 losses in a row: -50% (devastating but recoverable)\n- 20 trades with 55% win rate: +10% net\n- 50 trades with 55% win rate: +25% net\n- 100 trades with 55% win rate: +50% net\n\n**Patience + Math = Profit**"
      }
    ]
  }
}